{
  "type": "object",
  "properties": {
    "response": {
      "type": "object",
      "properties": {
        "notificationsCount": {
          "type": "array",
          "items": [
            {
              "type": "object",
              "properties": {
                "projectIdentity": {
                  "type": "string"
                },
                "unreadNotificationsCount": {
                  "type": "integer"
                }
              },
              "required": [
                "projectIdentity",
                "unreadNotificationsCount"
              ]
            }
          ]
        }
      },
      "required": [
        "notificationsCount"
      ]
    }
  },
  "required": [
    "response"
  ]
}