{
  "type": "object",
  "required": [
    "response"
  ],
  "properties": {
    "response": {
      "type": "object",
      "required": [
        "identity",
        "createdAt",
        "createdBy",
        "updatedAt",
        "customerIdentity",
        "siteIdentity",
        "apVersion",
        "active",
        "description",
        "subLicenses",
        "licensedModules",
        "createdByName"
      ],
      "optional": [
        "updatedBy",
        "updatedByName"
      ],
      "properties": {
        "identity": {
          "type": "string"
        },
        "createdAt": {
          "type": "string"
        },
        "createdBy": {
          "type": "string"
        },
        "updatedAt": {
          "type": "string"
        },
        "customerIdentity": {
          "type": "string"
        },
        "siteIdentity": {
          "type": "string"
        },
        "apVersion": {
          "type": "string"
        },
        "active": {
          "type": "boolean"
        },
        "description": {
          "type": "string"
        },
        "subLicenses": {
          "type": "array",
          "items": {
            "type": "object",
            "required": [
              "identity",
              "createdAt",
              "createdBy",
              "name",
              "uuid",
              "licensedModuleNames",
              "maxNumUsers",
              "numPurchasedUsers",
              "numAssignedUsers",
              "expiresAt"
            ],
            "properties": {
              "identity": {
                "type": "string"
              },
              "createdAt": {
                "type": "string"
              },
              "createdBy": {
                "type": "string"
              },
              "name": {
                "type": "string"
              },
              "uuid": {
                "type": "string"
              },
              "licensedModuleNames": {
                "type": "array",
                "items": {}
              },
              "maxNumUsers": {
                "type": "integer"
              },
              "numPurchasedUsers": {
                "type": "integer"
              },
              "numAssignedUsers": {
                "type": "integer"
              },
              "expiresAt": {
                "type": "string"
              }
            }
          }
        },
        "licensedModules": {
          "type": "array",
          "items": {
            "type": "object",
            "properties": {
              "identity": {
                "type": "string"
              },
              "createdAt": {
                "type": "string"
              },
              "createdBy": {
                "type": "string"
              },
              "name": {
                "type": "string"
              }
            }
          }
        },
        "createdByName": {
          "type": "string"
        }
      }
    }
  }
}